{
  "frames": {
    "effects/fog": {
      "frame": {
        "x": 3,
        "y": 3,
        "w": 320,
        "h": 180
      },
      "rotated": false,
      "trimmed": false,
      "spriteSourceSize": {
        "x": 0,
        "y": 0,
        "w": 320,
        "h": 180
      },
      "sourceSize": {
        "w": 320,
        "h": 180
      },
      "pivot": {
        "x": 0.5,
        "y": 0.5
      }
    },
    "effects/raylight": {
      "frame": {
        "x": 3,
        "y": 189,
        "w": 216,
        "h": 102
      },
      "rotated": false,
      "trimmed": false,
      "spriteSourceSize": {
        "x": 0,
        "y": 0,
        "w": 216,
        "h": 102
      },
      "sourceSize": {
        "w": 216,
        "h": 102
      },
      "pivot": {
        "x": 0.5,
        "y": 0.5
      }
    },
    "effects/quicksand": {
      "frame": {
        "x": 329,
        "y": 3,
        "w": 256,
        "h": 32
      },
      "rotated": false,
      "trimmed": false,
      "spriteSourceSize": {
        "x": 0,
        "y": 0,
        "w": 256,
        "h": 32
      },
      "sourceSize": {
        "w": 256,
        "h": 32
      },
      "pivot": {
        "x": 0.5,
        "y": 0.5
      }
    },
    "doodads/big_tree": {
      "frame": {
        "x": 3,
        "y": 297,
        "w": 32,
        "h": 48
      },
      "rotated": false,
      "trimmed": false,
      "spriteSourceSize": {
        "x": 0,
        "y": 0,
        "w": 32,
        "h": 48
      },
      "sourceSize": {
        "w": 32,
        "h": 48
      },
      "pivot": {
        "x": 0.5,
        "y": 0.5
      }
    },
    "effects/cut": {
      "frame": {
        "x": 225,
        "y": 189,
        "w": 240,
        "h": 28
      },
      "rotated": false,
      "trimmed": false,
      "spriteSourceSize": {
        "x": 0,
        "y": 0,
        "w": 240,
        "h": 28
      },
      "sourceSize": {
        "w": 240,
        "h": 28
      },
      "pivot": {
        "x": 0.5,
        "y": 0.5
      }
    },
    "effects/flames": {
      "frame": {
        "x": 591,
        "y": 3,
        "w": 200,
        "h": 30
      },
      "rotated": false,
      "trimmed": false,
      "spriteSourceSize": {
        "x": 0,
        "y": 0,
        "w": 200,
        "h": 30
      },
      "sourceSize": {
        "w": 200,
        "h": 30
      },
      "pivot": {
        "x": 0.5,
        "y": 0.5
      }
    },
    "doodads/black-museum": {
      "frame": {
        "x": 3,
        "y": 351,
        "w": 64,
        "h": 48
      },
      "rotated": false,
      "trimmed": false,
      "spriteSourceSize": {
        "x": 0,
        "y": 0,
        "w": 64,
        "h": 48
      },
      "sourceSize": {
        "w": 64,
        "h": 48
      },
      "pivot": {
        "x": 0.5,
        "y": 0.5
      }
    },
    "doodads/museum": {
      "frame": {
        "x": 225,
        "y": 223,
        "w": 64,
        "h": 48
      },
      "rotated": false,
      "trimmed": false,
      "spriteSourceSize": {
        "x": 0,
        "y": 0,
        "w": 64,
        "h": 48
      },
      "sourceSize": {
        "w": 64,
        "h": 48
      },
      "pivot": {
        "x": 0.5,
        "y": 0.5
      }
    },
    "doodads/shack": {
      "frame": {
        "x": 329,
        "y": 41,
        "w": 48,
        "h": 48
      },
      "rotated": false,
      "trimmed": false,
      "spriteSourceSize": {
        "x": 0,
        "y": 0,
        "w": 48,
        "h": 48
      },
      "sourceSize": {
        "w": 48,
        "h": 48
      },
      "pivot": {
        "x": 0.5,
        "y": 0.5
      }
    },
    "effects/splode_0": {
      "frame": {
        "x": 471,
        "y": 41,
        "w": 40,
        "h": 40
      },
      "rotated": false,
      "trimmed": false,
      "spriteSourceSize": {
        "x": 0,
        "y": 0,
        "w": 40,
        "h": 40
      },
      "sourceSize": {
        "w": 40,
        "h": 40
      },
      "pivot": {
        "x": 0.5,
        "y": 0.5
      }
    },
    "effects/splode_1": {
      "frame": {
        "x": 591,
        "y": 39,
        "w": 40,
        "h": 40
      },
      "rotated": false,
      "trimmed": false,
      "spriteSourceSize": {
        "x": 0,
        "y": 0,
        "w": 40,
        "h": 40
      },
      "sourceSize": {
        "w": 40,
        "h": 40
      },
      "pivot": {
        "x": 0.5,
        "y": 0.5
      }
    },
    "effects/splode_2": {
      "frame": {
        "x": 797,
        "y": 3,
        "w": 40,
        "h": 40
      },
      "rotated": false,
      "trimmed": false,
      "spriteSourceSize": {
        "x": 0,
        "y": 0,
        "w": 40,
        "h": 40
      },
      "sourceSize": {
        "w": 40,
        "h": 40
      },
      "pivot": {
        "x": 0.5,
        "y": 0.5
      }
    },
    "effects/splode_3": {
      "frame": {
        "x": 3,
        "y": 405,
        "w": 40,
        "h": 40
      },
      "rotated": false,
      "trimmed": false,
      "spriteSourceSize": {
        "x": 0,
        "y": 0,
        "w": 40,
        "h": 40
      },
      "sourceSize": {
        "w": 40,
        "h": 40
      },
      "pivot": {
        "x": 0.5,
        "y": 0.5
      }
    },
    "effects/splode_4": {
      "frame": {
        "x": 41,
        "y": 297,
        "w": 40,
        "h": 40
      },
      "rotated": false,
      "trimmed": false,
      "spriteSourceSize": {
        "x": 0,
        "y": 0,
        "w": 40,
        "h": 40
      },
      "sourceSize": {
        "w": 40,
        "h": 40
      },
      "pivot": {
        "x": 0.5,
        "y": 0.5
      }
    },
    "effects/splode_5": {
      "frame": {
        "x": 225,
        "y": 277,
        "w": 40,
        "h": 40
      },
      "rotated": false,
      "trimmed": false,
      "spriteSourceSize": {
        "x": 0,
        "y": 0,
        "w": 40,
        "h": 40
      },
      "sourceSize": {
        "w": 40,
        "h": 40
      },
      "pivot": {
        "x": 0.5,
        "y": 0.5
      }
    },
    "effects/splode_6": {
      "frame": {
        "x": 295,
        "y": 223,
        "w": 40,
        "h": 40
      },
      "rotated": false,
      "trimmed": false,
      "spriteSourceSize": {
        "x": 0,
        "y": 0,
        "w": 40,
        "h": 40
      },
      "sourceSize": {
        "w": 40,
        "h": 40
      },
      "pivot": {
        "x": 0.5,
        "y": 0.5
      }
    },
    "effects/splode_7": {
      "frame": {
        "x": 329,
        "y": 95,
        "w": 40,
        "h": 40
      },
      "rotated": false,
      "trimmed": false,
      "spriteSourceSize": {
        "x": 0,
        "y": 0,
        "w": 40,
        "h": 40
      },
      "sourceSize": {
        "w": 40,
        "h": 40
      },
      "pivot": {
        "x": 0.5,
        "y": 0.5
      }
    },
    "effects/splode_8": {
      "frame": {
        "x": 471,
        "y": 87,
        "w": 40,
        "h": 40
      },
      "rotated": false,
      "trimmed": false,
      "spriteSourceSize": {
        "x": 0,
        "y": 0,
        "w": 40,
        "h": 40
      },
      "sourceSize": {
        "w": 40,
        "h": 40
      },
      "pivot": {
        "x": 0.5,
        "y": 0.5
      }
    },
    "doodads/deadtree": {
      "frame": {
        "x": 383,
        "y": 41,
        "w": 32,
        "h": 31
      },
      "rotated": false,
      "trimmed": false,
      "spriteSourceSize": {
        "x": 0,
        "y": 0,
        "w": 32,
        "h": 31
      },
      "sourceSize": {
        "w": 32,
        "h": 31
      },
      "pivot": {
        "x": 0.5,
        "y": 0.5
      }
    },
    "doodads/hole": {
      "frame": {
        "x": 517,
        "y": 85,
        "w": 32,
        "h": 32
      },
      "rotated": false,
      "trimmed": false,
      "spriteSourceSize": {
        "x": 0,
        "y": 0,
        "w": 32,
        "h": 32
      },
      "sourceSize": {
        "w": 32,
        "h": 32
      },
      "pivot": {
        "x": 0.5,
        "y": 0.5
      }
    },
    "effects/smoke_frame_1": {
      "frame": {
        "x": 843,
        "y": 3,
        "w": 32,
        "h": 32
      },
      "rotated": false,
      "trimmed": false,
      "spriteSourceSize": {
        "x": 0,
        "y": 0,
        "w": 32,
        "h": 32
      },
      "sourceSize": {
        "w": 32,
        "h": 32
      },
      "pivot": {
        "x": 0.5,
        "y": 0.5
      }
    },
    "effects/smoke_frame_2": {
      "frame": {
        "x": 637,
        "y": 39,
        "w": 32,
        "h": 32
      },
      "rotated": false,
      "trimmed": false,
      "spriteSourceSize": {
        "x": 0,
        "y": 0,
        "w": 32,
        "h": 32
      },
      "sourceSize": {
        "w": 32,
        "h": 32
      },
      "pivot": {
        "x": 0.5,
        "y": 0.5
      }
    },
    "effects/smoke_frame_3": {
      "frame": {
        "x": 3,
        "y": 451,
        "w": 32,
        "h": 32
      },
      "rotated": false,
      "trimmed": false,
      "spriteSourceSize": {
        "x": 0,
        "y": 0,
        "w": 32,
        "h": 32
      },
      "sourceSize": {
        "w": 32,
        "h": 32
      },
      "pivot": {
        "x": 0.5,
        "y": 0.5
      }
    },
    "effects/smoke_frame_4": {
      "frame": {
        "x": 49,
        "y": 405,
        "w": 32,
        "h": 32
      },
      "rotated": false,
      "trimmed": false,
      "spriteSourceSize": {
        "x": 0,
        "y": 0,
        "w": 32,
        "h": 32
      },
      "sourceSize": {
        "w": 32,
        "h": 32
      },
      "pivot": {
        "x": 0.5,
        "y": 0.5
      }
    },
    "effects/smoke_frame_5": {
      "frame": {
        "x": 271,
        "y": 277,
        "w": 32,
        "h": 32
      },
      "rotated": false,
      "trimmed": false,
      "spriteSourceSize": {
        "x": 0,
        "y": 0,
        "w": 32,
        "h": 32
      },
      "sourceSize": {
        "w": 32,
        "h": 32
      },
      "pivot": {
        "x": 0.5,
        "y": 0.5
      }
    },
    "effects/smoke_frame_6": {
      "frame": {
        "x": 87,
        "y": 323,
        "w": 32,
        "h": 32
      },
      "rotated": false,
      "trimmed": false,
      "spriteSourceSize": {
        "x": 0,
        "y": 0,
        "w": 32,
        "h": 32
      },
      "sourceSize": {
        "w": 32,
        "h": 32
      },
      "pivot": {
        "x": 0.5,
        "y": 0.5
      }
    },
    "doodads/well": {
      "frame": {
        "x": 341,
        "y": 223,
        "w": 28,
        "h": 29
      },
      "rotated": false,
      "trimmed": false,
      "spriteSourceSize": {
        "x": 0,
        "y": 0,
        "w": 28,
        "h": 29
      },
      "sourceSize": {
        "w": 28,
        "h": 29
      },
      "pivot": {
        "x": 0.5,
        "y": 0.5
      }
    },
    "doodads/anemone": {
      "frame": {
        "x": 329,
        "y": 141,
        "w": 16,
        "h": 16
      },
      "rotated": false,
      "trimmed": false,
      "spriteSourceSize": {
        "x": 0,
        "y": 0,
        "w": 16,
        "h": 16
      },
      "sourceSize": {
        "w": 16,
        "h": 16
      },
      "pivot": {
        "x": 0.5,
        "y": 0.5
      }
    },
    "doodads/blue_shroom": {
      "frame": {
        "x": 471,
        "y": 133,
        "w": 16,
        "h": 16
      },
      "rotated": false,
      "trimmed": false,
      "spriteSourceSize": {
        "x": 0,
        "y": 0,
        "w": 16,
        "h": 16
      },
      "sourceSize": {
        "w": 16,
        "h": 16
      },
      "pivot": {
        "x": 0.5,
        "y": 0.5
      }
    },
    "doodads/cactus": {
      "frame": {
        "x": 375,
        "y": 95,
        "w": 16,
        "h": 16
      },
      "rotated": false,
      "trimmed": false,
      "spriteSourceSize": {
        "x": 0,
        "y": 0,
        "w": 16,
        "h": 16
      },
      "sourceSize": {
        "w": 16,
        "h": 16
      },
      "pivot": {
        "x": 0.5,
        "y": 0.5
      }
    },
    "doodads/cactus2": {
      "frame": {
        "x": 421,
        "y": 41,
        "w": 16,
        "h": 16
      },
      "rotated": false,
      "trimmed": false,
      "spriteSourceSize": {
        "x": 0,
        "y": 0,
        "w": 16,
        "h": 16
      },
      "sourceSize": {
        "w": 16,
        "h": 16
      },
      "pivot": {
        "x": 0.5,
        "y": 0.5
      }
    },
    "doodads/cube": {
      "frame": {
        "x": 517,
        "y": 123,
        "w": 16,
        "h": 16
      },
      "rotated": false,
      "trimmed": false,
      "spriteSourceSize": {
        "x": 0,
        "y": 0,
        "w": 16,
        "h": 16
      },
      "sourceSize": {
        "w": 16,
        "h": 16
      },
      "pivot": {
        "x": 0.5,
        "y": 0.5
      }
    },
    "doodads/dark_grate": {
      "frame": {
        "x": 555,
        "y": 85,
        "w": 16,
        "h": 16
      },
      "rotated": false,
      "trimmed": false,
      "spriteSourceSize": {
        "x": 0,
        "y": 0,
        "w": 16,
        "h": 16
      },
      "sourceSize": {
        "w": 16,
        "h": 16
      },
      "pivot": {
        "x": 0.5,
        "y": 0.5
      }
    },
    "doodads/grate": {
      "frame": {
        "x": 517,
        "y": 41,
        "w": 16,
        "h": 16
      },
      "rotated": false,
      "trimmed": false,
      "spriteSourceSize": {
        "x": 0,
        "y": 0,
        "w": 16,
        "h": 16
      },
      "sourceSize": {
        "w": 16,
        "h": 16
      },
      "pivot": {
        "x": 0.5,
        "y": 0.5
      }
    },
    "doodads/green_shroom": {
      "frame": {
        "x": 843,
        "y": 41,
        "w": 16,
        "h": 16
      },
      "rotated": false,
      "trimmed": false,
      "spriteSourceSize": {
        "x": 0,
        "y": 0,
        "w": 16,
        "h": 16
      },
      "sourceSize": {
        "w": 16,
        "h": 16
      },
      "pivot": {
        "x": 0.5,
        "y": 0.5
      }
    },
    "doodads/sign": {
      "frame": {
        "x": 881,
        "y": 3,
        "w": 16,
        "h": 16
      },
      "rotated": false,
      "trimmed": false,
      "spriteSourceSize": {
        "x": 0,
        "y": 0,
        "w": 16,
        "h": 16
      },
      "sourceSize": {
        "w": 16,
        "h": 16
      },
      "pivot": {
        "x": 0.5,
        "y": 0.5
      }
    },
    "doodads/sign-blank": {
      "frame": {
        "x": 675,
        "y": 39,
        "w": 16,
        "h": 16
      },
      "rotated": false,
      "trimmed": false,
      "spriteSourceSize": {
        "x": 0,
        "y": 0,
        "w": 16,
        "h": 16
      },
      "sourceSize": {
        "w": 16,
        "h": 16
      },
      "pivot": {
        "x": 0.5,
        "y": 0.5
      }
    },
    "doodads/sign-eaten": {
      "frame": {
        "x": 637,
        "y": 77,
        "w": 16,
        "h": 16
      },
      "rotated": false,
      "trimmed": false,
      "spriteSourceSize": {
        "x": 0,
        "y": 0,
        "w": 16,
        "h": 16
      },
      "sourceSize": {
        "w": 16,
        "h": 16
      },
      "pivot": {
        "x": 0.5,
        "y": 0.5
      }
    },
    "doodads/sign-gold": {
      "frame": {
        "x": 3,
        "y": 489,
        "w": 16,
        "h": 16
      },
      "rotated": false,
      "trimmed": false,
      "spriteSourceSize": {
        "x": 0,
        "y": 0,
        "w": 16,
        "h": 16
      },
      "sourceSize": {
        "w": 16,
        "h": 16
      },
      "pivot": {
        "x": 0.5,
        "y": 0.5
      }
    },
    "doodads/sign-metal": {
      "frame": {
        "x": 41,
        "y": 451,
        "w": 16,
        "h": 16
      },
      "rotated": false,
      "trimmed": false,
      "spriteSourceSize": {
        "x": 0,
        "y": 0,
        "w": 16,
        "h": 16
      },
      "sourceSize": {
        "w": 16,
        "h": 16
      },
      "pivot": {
        "x": 0.5,
        "y": 0.5
      }
    },
    "doodads/sign-metal-alt": {
      "frame": {
        "x": 271,
        "y": 315,
        "w": 16,
        "h": 16
      },
      "rotated": false,
      "trimmed": false,
      "spriteSourceSize": {
        "x": 0,
        "y": 0,
        "w": 16,
        "h": 16
      },
      "sourceSize": {
        "w": 16,
        "h": 16
      },
      "pivot": {
        "x": 0.5,
        "y": 0.5
      }
    },
    "doodads/small_evergreen": {
      "frame": {
        "x": 309,
        "y": 269,
        "w": 16,
        "h": 16
      },
      "rotated": false,
      "trimmed": false,
      "spriteSourceSize": {
        "x": 0,
        "y": 0,
        "w": 16,
        "h": 16
      },
      "sourceSize": {
        "w": 16,
        "h": 16
      },
      "pivot": {
        "x": 0.5,
        "y": 0.5
      }
    },
    "doodads/stairdown": {
      "frame": {
        "x": 87,
        "y": 361,
        "w": 16,
        "h": 16
      },
      "rotated": false,
      "trimmed": false,
      "spriteSourceSize": {
        "x": 0,
        "y": 0,
        "w": 16,
        "h": 16
      },
      "sourceSize": {
        "w": 16,
        "h": 16
      },
      "pivot": {
        "x": 0.5,
        "y": 0.5
      }
    },
    "doodads/stairup": {
      "frame": {
        "x": 87,
        "y": 297,
        "w": 16,
        "h": 16
      },
      "rotated": false,
      "trimmed": false,
      "spriteSourceSize": {
        "x": 0,
        "y": 0,
        "w": 16,
        "h": 16
      },
      "sourceSize": {
        "w": 16,
        "h": 16
      },
      "pivot": {
        "x": 0.5,
        "y": 0.5
      }
    },
    "doodads/table": {
      "frame": {
        "x": 125,
        "y": 297,
        "w": 16,
        "h": 15
      },
      "rotated": false,
      "trimmed": false,
      "spriteSourceSize": {
        "x": 0,
        "y": 0,
        "w": 16,
        "h": 15
      },
      "sourceSize": {
        "w": 16,
        "h": 15
      },
      "pivot": {
        "x": 0.5,
        "y": 0.5
      }
    },
    "doodads/urchin": {
      "frame": {
        "x": 341,
        "y": 258,
        "w": 16,
        "h": 16
      },
      "rotated": false,
      "trimmed": false,
      "spriteSourceSize": {
        "x": 0,
        "y": 0,
        "w": 16,
        "h": 16
      },
      "sourceSize": {
        "w": 16,
        "h": 16
      },
      "pivot": {
        "x": 0.5,
        "y": 0.5
      }
    },
    "effects/sparkle": {
      "frame": {
        "x": 375,
        "y": 223,
        "w": 16,
        "h": 16
      },
      "rotated": false,
      "trimmed": false,
      "spriteSourceSize": {
        "x": 0,
        "y": 0,
        "w": 16,
        "h": 16
      },
      "sourceSize": {
        "w": 16,
        "h": 16
      },
      "pivot": {
        "x": 0.5,
        "y": 0.5
      }
    },
    "floors/aqua": {
      "frame": {
        "x": 329,
        "y": 163,
        "w": 16,
        "h": 16
      },
      "rotated": false,
      "trimmed": false,
      "spriteSourceSize": {
        "x": 0,
        "y": 0,
        "w": 16,
        "h": 16
      },
      "sourceSize": {
        "w": 16,
        "h": 16
      },
      "pivot": {
        "x": 0.5,
        "y": 0.5
      }
    },
    "floors/bones": {
      "frame": {
        "x": 471,
        "y": 155,
        "w": 16,
        "h": 16
      },
      "rotated": false,
      "trimmed": false,
      "spriteSourceSize": {
        "x": 0,
        "y": 0,
        "w": 16,
        "h": 16
      },
      "sourceSize": {
        "w": 16,
        "h": 16
      },
      "pivot": {
        "x": 0.5,
        "y": 0.5
      }
    },
    "floors/clouds": {
      "frame": {
        "x": 351,
        "y": 141,
        "w": 16,
        "h": 16
      },
      "rotated": false,
      "trimmed": false,
      "spriteSourceSize": {
        "x": 0,
        "y": 0,
        "w": 16,
        "h": 16
      },
      "sourceSize": {
        "w": 16,
        "h": 16
      },
      "pivot": {
        "x": 0.5,
        "y": 0.5
      }
    },
    "floors/crackedseaice": {
      "frame": {
        "x": 375,
        "y": 117,
        "w": 16,
        "h": 16
      },
      "rotated": false,
      "trimmed": false,
      "spriteSourceSize": {
        "x": 0,
        "y": 0,
        "w": 16,
        "h": 16
      },
      "sourceSize": {
        "w": 16,
        "h": 16
      },
      "pivot": {
        "x": 0.5,
        "y": 0.5
      }
    },
    "floors/crag": {
      "frame": {
        "x": 397,
        "y": 78,
        "w": 16,
        "h": 16
      },
      "rotated": false,
      "trimmed": false,
      "spriteSourceSize": {
        "x": 0,
        "y": 0,
        "w": 16,
        "h": 16
      },
      "sourceSize": {
        "w": 16,
        "h": 16
      },
      "pivot": {
        "x": 0.5,
        "y": 0.5
      }
    },
    "floors/desert": {
      "frame": {
        "x": 421,
        "y": 63,
        "w": 16,
        "h": 16
      },
      "rotated": false,
      "trimmed": false,
      "spriteSourceSize": {
        "x": 0,
        "y": 0,
        "w": 16,
        "h": 16
      },
      "sourceSize": {
        "w": 16,
        "h": 16
      },
      "pivot": {
        "x": 0.5,
        "y": 0.5
      }
    },
    "floors/dirt": {
      "frame": {
        "x": 443,
        "y": 41,
        "w": 16,
        "h": 16
      },
      "rotated": false,
      "trimmed": false,
      "spriteSourceSize": {
        "x": 0,
        "y": 0,
        "w": 16,
        "h": 16
      },
      "sourceSize": {
        "w": 16,
        "h": 16
      },
      "pivot": {
        "x": 0.5,
        "y": 0.5
      }
    },
    "floors/dirtpatch": {
      "frame": {
        "x": 539,
        "y": 123,
        "w": 16,
        "h": 16
      },
      "rotated": false,
      "trimmed": false,
      "spriteSourceSize": {
        "x": 0,
        "y": 0,
        "w": 16,
        "h": 16
      },
      "sourceSize": {
        "w": 16,
        "h": 16
      },
      "pivot": {
        "x": 0.5,
        "y": 0.5
      }
    },
    "floors/grass": {
      "frame": {
        "x": 493,
        "y": 145,
        "w": 16,
        "h": 16
      },
      "rotated": false,
      "trimmed": false,
      "spriteSourceSize": {
        "x": 0,
        "y": 0,
        "w": 16,
        "h": 16
      },
      "sourceSize": {
        "w": 16,
        "h": 16
      },
      "pivot": {
        "x": 0.5,
        "y": 0.5
      }
    },
    "floors/gravel": {
      "frame": {
        "x": 517,
        "y": 63,
        "w": 16,
        "h": 16
      },
      "rotated": false,
      "trimmed": false,
      "spriteSourceSize": {
        "x": 0,
        "y": 0,
        "w": 16,
        "h": 16
      },
      "sourceSize": {
        "w": 16,
        "h": 16
      },
      "pivot": {
        "x": 0.5,
        "y": 0.5
      }
    },
    "floors/graytile": {
      "frame": {
        "x": 539,
        "y": 41,
        "w": 16,
        "h": 16
      },
      "rotated": false,
      "trimmed": false,
      "spriteSourceSize": {
        "x": 0,
        "y": 0,
        "w": 16,
        "h": 16
      },
      "sourceSize": {
        "w": 16,
        "h": 16
      },
      "pivot": {
        "x": 0.5,
        "y": 0.5
      }
    },
    "floors/housetile": {
      "frame": {
        "x": 865,
        "y": 41,
        "w": 16,
        "h": 16
      },
      "rotated": false,
      "trimmed": false,
      "spriteSourceSize": {
        "x": 0,
        "y": 0,
        "w": 16,
        "h": 16
      },
      "sourceSize": {
        "w": 16,
        "h": 16
      },
      "pivot": {
        "x": 0.5,
        "y": 0.5
      }
    },
    "floors/mulch": {
      "frame": {
        "x": 675,
        "y": 63,
        "w": 16,
        "h": 16
      },
      "rotated": false,
      "trimmed": false,
      "spriteSourceSize": {
        "x": 0,
        "y": 0,
        "w": 16,
        "h": 16
      },
      "sourceSize": {
        "w": 16,
        "h": 16
      },
      "pivot": {
        "x": 0.5,
        "y": 0.5
      }
    },
    "floors/seaice": {
      "frame": {
        "x": 903,
        "y": 3,
        "w": 16,
        "h": 16
      },
      "rotated": false,
      "trimmed": false,
      "spriteSourceSize": {
        "x": 0,
        "y": 0,
        "w": 16,
        "h": 16
      },
      "sourceSize": {
        "w": 16,
        "h": 16
      },
      "pivot": {
        "x": 0.5,
        "y": 0.5
      }
    },
    "floors/underbrush": {
      "frame": {
        "x": 697,
        "y": 39,
        "w": 16,
        "h": 16
      },
      "rotated": false,
      "trimmed": false,
      "spriteSourceSize": {
        "x": 0,
        "y": 0,
        "w": 16,
        "h": 16
      },
      "sourceSize": {
        "w": 16,
        "h": 16
      },
      "pivot": {
        "x": 0.5,
        "y": 0.5
      }
    },
    "obstacles/rock": {
      "frame": {
        "x": 577,
        "y": 99,
        "w": 16,
        "h": 16
      },
      "rotated": false,
      "trimmed": false,
      "spriteSourceSize": {
        "x": 0,
        "y": 0,
        "w": 16,
        "h": 16
      },
      "sourceSize": {
        "w": 16,
        "h": 16
      },
      "pivot": {
        "x": 0.5,
        "y": 0.5
      }
    },
    "obstacles/shrubbery": {
      "frame": {
        "x": 3,
        "y": 511,
        "w": 16,
        "h": 16
      },
      "rotated": false,
      "trimmed": false,
      "spriteSourceSize": {
        "x": 0,
        "y": 0,
        "w": 16,
        "h": 16
      },
      "sourceSize": {
        "w": 16,
        "h": 16
      },
      "pivot": {
        "x": 0.5,
        "y": 0.5
      }
    },
    "trim/bordertrim": {
      "frame": {
        "x": 25,
        "y": 489,
        "w": 16,
        "h": 16
      },
      "rotated": false,
      "trimmed": false,
      "spriteSourceSize": {
        "x": 0,
        "y": 0,
        "w": 16,
        "h": 16
      },
      "sourceSize": {
        "w": 16,
        "h": 16
      },
      "pivot": {
        "x": 0.5,
        "y": 0.5
      }
    },
    "walls/90s": {
      "frame": {
        "x": 63,
        "y": 443,
        "w": 16,
        "h": 16
      },
      "rotated": false,
      "trimmed": false,
      "spriteSourceSize": {
        "x": 0,
        "y": 0,
        "w": 16,
        "h": 16
      },
      "sourceSize": {
        "w": 16,
        "h": 16
      },
      "pivot": {
        "x": 0.5,
        "y": 0.5
      }
    },
    "walls/astrocrag": {
      "frame": {
        "x": 293,
        "y": 315,
        "w": 16,
        "h": 16
      },
      "rotated": false,
      "trimmed": false,
      "spriteSourceSize": {
        "x": 0,
        "y": 0,
        "w": 16,
        "h": 16
      },
      "sourceSize": {
        "w": 16,
        "h": 16
      },
      "pivot": {
        "x": 0.5,
        "y": 0.5
      }
    },
    "walls/blocklily": {
      "frame": {
        "x": 125,
        "y": 337,
        "w": 16,
        "h": 16
      },
      "rotated": false,
      "trimmed": false,
      "spriteSourceSize": {
        "x": 0,
        "y": 0,
        "w": 16,
        "h": 16
      },
      "sourceSize": {
        "w": 16,
        "h": 16
      },
      "pivot": {
        "x": 0.5,
        "y": 0.5
      }
    },
    "walls/boulder": {
      "frame": {
        "x": 87,
        "y": 383,
        "w": 16,
        "h": 16
      },
      "rotated": false,
      "trimmed": false,
      "spriteSourceSize": {
        "x": 0,
        "y": 0,
        "w": 16,
        "h": 16
      },
      "sourceSize": {
        "w": 16,
        "h": 16
      },
      "pivot": {
        "x": 0.5,
        "y": 0.5
      }
    },
    "walls/bush": {
      "frame": {
        "x": 109,
        "y": 361,
        "w": 16,
        "h": 16
      },
      "rotated": false,
      "trimmed": false,
      "spriteSourceSize": {
        "x": 0,
        "y": 0,
        "w": 16,
        "h": 16
      },
      "sourceSize": {
        "w": 16,
        "h": 16
      },
      "pivot": {
        "x": 0.5,
        "y": 0.5
      }
    },
    "walls/bush2": {
      "frame": {
        "x": 147,
        "y": 297,
        "w": 16,
        "h": 16
      },
      "rotated": false,
      "trimmed": false,
      "spriteSourceSize": {
        "x": 0,
        "y": 0,
        "w": 16,
        "h": 16
      },
      "sourceSize": {
        "w": 16,
        "h": 16
      },
      "pivot": {
        "x": 0.5,
        "y": 0.5
      }
    },
    "walls/bushes": {
      "frame": {
        "x": 363,
        "y": 258,
        "w": 16,
        "h": 16
      },
      "rotated": false,
      "trimmed": false,
      "spriteSourceSize": {
        "x": 0,
        "y": 0,
        "w": 16,
        "h": 16
      },
      "sourceSize": {
        "w": 16,
        "h": 16
      },
      "pivot": {
        "x": 0.5,
        "y": 0.5
      }
    },
    "walls/chargedwall": {
      "frame": {
        "x": 331,
        "y": 280,
        "w": 16,
        "h": 16
      },
      "rotated": false,
      "trimmed": false,
      "spriteSourceSize": {
        "x": 0,
        "y": 0,
        "w": 16,
        "h": 16
      },
      "sourceSize": {
        "w": 16,
        "h": 16
      },
      "pivot": {
        "x": 0.5,
        "y": 0.5
      }
    },
    "walls/cobble": {
      "frame": {
        "x": 397,
        "y": 223,
        "w": 16,
        "h": 16
      },
      "rotated": false,
      "trimmed": false,
      "spriteSourceSize": {
        "x": 0,
        "y": 0,
        "w": 16,
        "h": 16
      },
      "sourceSize": {
        "w": 16,
        "h": 16
      },
      "pivot": {
        "x": 0.5,
        "y": 0.5
      }
    },
    "walls/coralwall": {
      "frame": {
        "x": 471,
        "y": 177,
        "w": 16,
        "h": 16
      },
      "rotated": false,
      "trimmed": false,
      "spriteSourceSize": {
        "x": 0,
        "y": 0,
        "w": 16,
        "h": 16
      },
      "sourceSize": {
        "w": 16,
        "h": 16
      },
      "pivot": {
        "x": 0.5,
        "y": 0.5
      }
    },
    "walls/deco": {
      "frame": {
        "x": 351,
        "y": 163,
        "w": 16,
        "h": 16
      },
      "rotated": false,
      "trimmed": false,
      "spriteSourceSize": {
        "x": 0,
        "y": 0,
        "w": 16,
        "h": 16
      },
      "sourceSize": {
        "w": 16,
        "h": 16
      },
      "pivot": {
        "x": 0.5,
        "y": 0.5
      }
    },
    "walls/fortwall": {
      "frame": {
        "x": 373,
        "y": 141,
        "w": 16,
        "h": 16
      },
      "rotated": false,
      "trimmed": false,
      "spriteSourceSize": {
        "x": 0,
        "y": 0,
        "w": 16,
        "h": 16
      },
      "sourceSize": {
        "w": 16,
        "h": 16
      },
      "pivot": {
        "x": 0.5,
        "y": 0.5
      }
    },
    "walls/heartstone": {
      "frame": {
        "x": 397,
        "y": 100,
        "w": 16,
        "h": 16
      },
      "rotated": false,
      "trimmed": false,
      "spriteSourceSize": {
        "x": 0,
        "y": 0,
        "w": 16,
        "h": 16
      },
      "sourceSize": {
        "w": 16,
        "h": 16
      },
      "pivot": {
        "x": 0.5,
        "y": 0.5
      }
    },
    "walls/hedge/hedge_bottom_left": {
      "frame": {
        "x": 419,
        "y": 85,
        "w": 16,
        "h": 16
      },
      "rotated": false,
      "trimmed": false,
      "spriteSourceSize": {
        "x": 0,
        "y": 0,
        "w": 16,
        "h": 16
      },
      "sourceSize": {
        "w": 16,
        "h": 16
      },
      "pivot": {
        "x": 0.5,
        "y": 0.5
      }
    },
    "walls/hedge/hedge_bottom_right": {
      "frame": {
        "x": 443,
        "y": 63,
        "w": 16,
        "h": 16
      },
      "rotated": false,
      "trimmed": false,
      "spriteSourceSize": {
        "x": 0,
        "y": 0,
        "w": 16,
        "h": 16
      },
      "sourceSize": {
        "w": 16,
        "h": 16
      },
      "pivot": {
        "x": 0.5,
        "y": 0.5
      }
    },
    "walls/hedge/hedge_left": {
      "frame": {
        "x": 493,
        "y": 167,
        "w": 16,
        "h": 16
      },
      "rotated": false,
      "trimmed": false,
      "spriteSourceSize": {
        "x": 0,
        "y": 0,
        "w": 16,
        "h": 16
      },
      "sourceSize": {
        "w": 16,
        "h": 16
      },
      "pivot": {
        "x": 0.5,
        "y": 0.5
      }
    },
    "walls/hedge/hedge_right": {
      "frame": {
        "x": 515,
        "y": 145,
        "w": 16,
        "h": 16
      },
      "rotated": false,
      "trimmed": false,
      "spriteSourceSize": {
        "x": 0,
        "y": 0,
        "w": 16,
        "h": 16
      },
      "sourceSize": {
        "w": 16,
        "h": 16
      },
      "pivot": {
        "x": 0.5,
        "y": 0.5
      }
    },
    "walls/hedge/hedge_top": {
      "frame": {
        "x": 539,
        "y": 63,
        "w": 16,
        "h": 16
      },
      "rotated": false,
      "trimmed": false,
      "spriteSourceSize": {
        "x": 0,
        "y": 0,
        "w": 16,
        "h": 16
      },
      "sourceSize": {
        "w": 16,
        "h": 16
      },
      "pivot": {
        "x": 0.5,
        "y": 0.5
      }
    },
    "walls/hedge/hedge_top_left": {
      "frame": {
        "x": 561,
        "y": 41,
        "w": 16,
        "h": 16
      },
      "rotated": false,
      "trimmed": false,
      "spriteSourceSize": {
        "x": 0,
        "y": 0,
        "w": 16,
        "h": 16
      },
      "sourceSize": {
        "w": 16,
        "h": 16
      },
      "pivot": {
        "x": 0.5,
        "y": 0.5
      }
    },
    "walls/hedge/hedge_top_right": {
      "frame": {
        "x": 887,
        "y": 25,
        "w": 16,
        "h": 16
      },
      "rotated": false,
      "trimmed": false,
      "spriteSourceSize": {
        "x": 0,
        "y": 0,
        "w": 16,
        "h": 16
      },
      "sourceSize": {
        "w": 16,
        "h": 16
      },
      "pivot": {
        "x": 0.5,
        "y": 0.5
      }
    },
    "walls/lavawall": {
      "frame": {
        "x": 697,
        "y": 63,
        "w": 16,
        "h": 16
      },
      "rotated": false,
      "trimmed": false,
      "spriteSourceSize": {
        "x": 0,
        "y": 0,
        "w": 16,
        "h": 16
      },
      "sourceSize": {
        "w": 16,
        "h": 16
      },
      "pivot": {
        "x": 0.5,
        "y": 0.5
      }
    },
    "walls/museumwall": {
      "frame": {
        "x": 659,
        "y": 85,
        "w": 16,
        "h": 16
      },
      "rotated": false,
      "trimmed": false,
      "spriteSourceSize": {
        "x": 0,
        "y": 0,
        "w": 16,
        "h": 16
      },
      "sourceSize": {
        "w": 16,
        "h": 16
      },
      "pivot": {
        "x": 0.5,
        "y": 0.5
      }
    },
    "walls/museumwall1": {
      "frame": {
        "x": 925,
        "y": 3,
        "w": 16,
        "h": 16
      },
      "rotated": false,
      "trimmed": false,
      "spriteSourceSize": {
        "x": 0,
        "y": 0,
        "w": 16,
        "h": 16
      },
      "sourceSize": {
        "w": 16,
        "h": 16
      },
      "pivot": {
        "x": 0.5,
        "y": 0.5
      }
    },
    "walls/museumwall2": {
      "frame": {
        "x": 719,
        "y": 39,
        "w": 16,
        "h": 16
      },
      "rotated": false,
      "trimmed": false,
      "spriteSourceSize": {
        "x": 0,
        "y": 0,
        "w": 16,
        "h": 16
      },
      "sourceSize": {
        "w": 16,
        "h": 16
      },
      "pivot": {
        "x": 0.5,
        "y": 0.5
      }
    },
    "walls/museumwall4": {
      "frame": {
        "x": 599,
        "y": 85,
        "w": 16,
        "h": 16
      },
      "rotated": false,
      "trimmed": false,
      "spriteSourceSize": {
        "x": 0,
        "y": 0,
        "w": 16,
        "h": 16
      },
      "sourceSize": {
        "w": 16,
        "h": 16
      },
      "pivot": {
        "x": 0.5,
        "y": 0.5
      }
    },
    "walls/museumwall5": {
      "frame": {
        "x": 561,
        "y": 121,
        "w": 16,
        "h": 16
      },
      "rotated": false,
      "trimmed": false,
      "spriteSourceSize": {
        "x": 0,
        "y": 0,
        "w": 16,
        "h": 16
      },
      "sourceSize": {
        "w": 16,
        "h": 16
      },
      "pivot": {
        "x": 0.5,
        "y": 0.5
      }
    },
    "walls/museumwall6": {
      "frame": {
        "x": 3,
        "y": 533,
        "w": 16,
        "h": 16
      },
      "rotated": false,
      "trimmed": false,
      "spriteSourceSize": {
        "x": 0,
        "y": 0,
        "w": 16,
        "h": 16
      },
      "sourceSize": {
        "w": 16,
        "h": 16
      },
      "pivot": {
        "x": 0.5,
        "y": 0.5
      }
    },
    "walls/rockwall": {
      "frame": {
        "x": 25,
        "y": 511,
        "w": 16,
        "h": 16
      },
      "rotated": false,
      "trimmed": false,
      "spriteSourceSize": {
        "x": 0,
        "y": 0,
        "w": 16,
        "h": 16
      },
      "sourceSize": {
        "w": 16,
        "h": 16
      },
      "pivot": {
        "x": 0.5,
        "y": 0.5
      }
    },
    "walls/stump": {
      "frame": {
        "x": 47,
        "y": 473,
        "w": 16,
        "h": 16
      },
      "rotated": false,
      "trimmed": false,
      "spriteSourceSize": {
        "x": 0,
        "y": 0,
        "w": 16,
        "h": 16
      },
      "sourceSize": {
        "w": 16,
        "h": 16
      },
      "pivot": {
        "x": 0.5,
        "y": 0.5
      }
    },
    "walls/zydeco": {
      "frame": {
        "x": 85,
        "y": 443,
        "w": 16,
        "h": 16
      },
      "rotated": false,
      "trimmed": false,
      "spriteSourceSize": {
        "x": 0,
        "y": 0,
        "w": 16,
        "h": 16
      },
      "sourceSize": {
        "w": 16,
        "h": 16
      },
      "pivot": {
        "x": 0.5,
        "y": 0.5
      }
    },
    "doodads/pitfall": {
      "frame": {
        "x": 147,
        "y": 337,
        "w": 15,
        "h": 14
      },
      "rotated": false,
      "trimmed": false,
      "spriteSourceSize": {
        "x": 0,
        "y": 0,
        "w": 15,
        "h": 14
      },
      "sourceSize": {
        "w": 15,
        "h": 14
      },
      "pivot": {
        "x": 0.5,
        "y": 0.5
      }
    },
    "walls/succulent": {
      "frame": {
        "x": 421,
        "y": 41,
        "w": 16,
        "h": 16
      },
      "rotated": false,
      "trimmed": false,
      "spriteSourceSize": {
        "x": 0,
        "y": 0,
        "w": 16,
        "h": 16
      },
      "sourceSize": {
        "w": 16,
        "h": 16
      },
      "pivot": {
        "x": 0.5,
        "y": 0.5
      }
    }
  },
  "meta": {
    "app": "http://github.com/odrick/free-tex-packer-core",
    "version": "0.3.5",
    "image": "environment.webp",
    "format": "RGBA8888",
    "size": {
      "w": 1024,
      "h": 1024
    },
    "scale": 1
  }
}