{
  "id": "blot",
  "name": "Blot",
  "type": "dialogue",
  "metadata": {
    "description": "A depressed character with everything going for him.",
    "created": "2025-10-31T00:00:00.000Z",
    "version": "1.0.0",
    "category": "gossip"
  },
  "display": {
  "sprite": "characters/npcs/gossip/blot.png",
  "portrait": "characters/npcs/portraits/blotface.png",
  "portraitBackground": "#2F2F2F",
    "tileType": "BLOT"
  },
  "placement": {
    "zone": null,
    "x": null,
    "y": null,
    "dimension": 0,
    "spawnLogic": "procedural",
    "spawnWeight": 0.005,
    "level": 2
  },
  "interaction": {
    "type": "dialogue",
    "cycleMode": "sequential",
    "dialogueTree": [
      {
        "id": "msg_0",
        "text": "Got a promotion, dream house, loving partner. Still wake up sad. Maybe happiness is broken?",
        "buttonText": "Sorry..."
      },
      {
        "id": "msg_1",
        "text": "Everything's perfect on paper. So why does it feel like I'm living in a really boring dystopia?",
        "buttonText": "I feel that."
      },
      {
        "id": "msg_2",
        "text": "Achieved all my goals by 30. Turns out goals were just distractions from the void. Cool.",
        "buttonText": "Relatable."
      }
    ]
  },
  "behavior": {
    "movementType": "stationary",
    "walkable": false
  },
  "audio": {
    "voicePitch": 110
  }
}
