{
  "id": "blotter",
  "name": "Blotter",
  "type": "dialogue",
  "metadata": {
    "description": "The slimiest fish you ever met.",
    "created": "2025-10-31T00:00:00.000Z",
    "version": "1.0.0",
    "category": "gossip"
  },
  "display": {
  "sprite": "characters/npcs/gossip/blotter.png",
  "portrait": "characters/npcs/portraits/blotterface.png",
  "portraitBackground": "#32CD32",
    "tileType": "BLOTTER"
  },
  "placement": {
    "zone": null,
    "x": null,
    "y": null,
    "dimension": 2,
    "spawnLogic": "procedural",
    "spawnWeight": 0.005,
    "level": 3
  },
  "interaction": {
    "type": "dialogue",
    "cycleMode": "sequential",
    "dialogueTree": [
      {
        "id": "msg_0",
        "text": "Have you heard of PHISHCOIN?",
        "buttonText": "No."
      },
      {
        "id": "msg_1",
        "text": "For 50 points you can get 50 PHISHCOIN and the rights to a gallery of original DIGITAL ART.",
        "buttonText": "Really?"
      },
      {
        "id": "msg_2",
        "text": "Can I borrow 10 points?",
        "buttonText": "Sorry."
      }
    ]
  },
  "behavior": {
    "movementType": "stationary",
    "walkable": false
  },
  "audio": {
    "voicePitch": 95
  }
}
