{
  "id": "palimpsest",
  "name": "Palimpsest",
  "type": "dialogue",
  "metadata": {
    "description": "A lizard who has nothing to do with any of the lizard enemies in the game. Stop suggesting it.",
    "created": "2025-11-11T00:00:00.000Z",
    "version": "1.0.0",
    "category": "gossip"
  },
  "display": {
    "sprite": "characters/npcs/gossip/palimpsest.png",
    "portrait": "characters/npcs/portraits/palimpsestface.png",
    "tileType": "PALIMPSEST",
    "portraitBackground": "#4da6ff"
  },
  "placement": {
    "zone": null,
    "x": null,
    "y": null,
    "dimension": 0,
    "spawnLogic": "procedural",
    "spawnWeight": 0.005,
    "level": 1
  },
  "interaction": {
    "type": "dialogue",
    "cycleMode": "sequential",
    "dialogueTree": [
      {
        "id": "msg_0",
        "text": "You didn't try to CAPTURE me? Did you?",
        "buttonText": "Maybe."
      },
      {
        "id": "msg_1",
        "text": "I have nothing to do with the lizards. I'm my own thing.",
        "buttonText": "No?"
      },
      {
        "id": "msg_2",
        "text": "Every time I look at a LIZARDY I get sick. Ruins my day. Move left and right or something. Jesus.",
        "buttonText": "Got it."
      }
    ]
  },
  "behavior": {
    "movementType": "stationary",
    "walkable": false
  },
  "audio": {
    "voicePitch": 104,
    "voicePattern": {
      "notes": [
        220,
        246.94,
        261.63,
        293.66
      ],
      "wave1": "sawtooth",
      "wave2": "square",
      "rhythmVariation": [
        1,
        1,
        1,
        1
      ],
      "gain": 0.22,
      "attack": 0.005,
      "decay": 0.11
    }
  }
}
